pylibxdaq-0.4.2.dist-info/RECORD
pylibxdaq-0.4.2.dist-info/WHEEL
pylibxdaq-0.4.2.dist-info/top_level.txt
pylibxdaq-0.4.2.dist-info/METADATA
pylibxdaq-0.4.2.dist-info/licenses/LICENSE
pylibxdaq/device.py
pylibxdaq/pyxdaq_device.pyi
pylibxdaq/pyxdaq_device.cpython-313-darwin.so
pylibxdaq/py.typed
pylibxdaq/resources/rhd.bit
pylibxdaq/resources/rhs.bit
pylibxdaq/managers/__init__.py
pylibxdaq/managers/libthor_device_manager.dylib
pylibxdaq/managers/libok_device_manager.dylib
pylibxdaq/managers/libokFrontPanel.dylib
