Metadata-Version: 2.4
Name: pylibxdaq
Version: 0.4.2
License-Expression: MIT
Project-URL: Homepage, https://github.com/kontex-neuro/pylibxdaq
Classifier: Programming Language :: Python :: 3.11
Classifier: Programming Language :: Python :: 3.12
Classifier: Programming Language :: Python :: 3.13
License-File: LICENSE
Requires-Dist: typing_extensions
Dynamic: license-file
